quark/circuit/__init__.py
quark/circuit/backend.py
quark/circuit/basepasses.py
quark/circuit/dag.py
quark/circuit/decompose.py
quark/circuit/layout.py
quark/circuit/matrix.py
quark/circuit/optimize.py
quark/circuit/quantumcircuit.py
quark/circuit/quantumcircuit_helpers.py
quark/circuit/routing.py
quark/circuit/schedule.py
quark/circuit/translate.py
quark/circuit/transpiler.py
quark/circuit/utils.py
quarkcircuit-0.4.1.dist-info/METADATA
quarkcircuit-0.4.1.dist-info/WHEEL
quarkcircuit-0.4.1.dist-info/top_level.txt
quarkcircuit-0.4.1.dist-info/RECORD
