Metadata-Version: 2.4
Name: quarkcircuit
Version: 0.4.1
Summary: Construction, visualization, and transpilation of quantum circuits
Author-email: Xiaoxiao Xiao <xiaoxx@baqis.ac.cn>
License-Expression: MIT
Requires-Python: >=3.12
Requires-Dist: numpy
Requires-Dist: scipy
Requires-Dist: networkx
Requires-Dist: quarkstudio
